pychute/__init__.py
pychute/config.py
pychute/helpers.py
pychute/main.py
pychute-0.1.5.dist-info/licenses/LICENSE
pychute-0.1.5.dist-info/METADATA
pychute-0.1.5.dist-info/WHEEL
pychute-0.1.5.dist-info/top_level.txt
pychute-0.1.5.dist-info/RECORD
