Metadata-Version: 2.4
Name: pychute
Version: 0.1.5
Summary: A library that helps downloading videos from bitchute.com
Home-page: http://github.com/paichiwo/pychute
Author: Lukasz Zerucha
Author-email: Lukasz Zerucha <lzerucha@gmail.com>
License: MIT License
Project-URL: Homepage, https://github.com/paichiwo/pychute
Project-URL: Issues, https://github.com/paichiwo/pychute/issues
Classifier: Programming Language :: Python :: 3
Classifier: License :: OSI Approved :: MIT License
Classifier: Operating System :: OS Independent
Requires-Python: >=3.8
License-File: LICENSE
Requires-Dist: selenium
Requires-Dist: beautifulsoup4
Dynamic: author
Dynamic: home-page
Dynamic: license-file
